cern_oa/__init__.py
cern_oa/dep_graph.py
dependency_analyzer-1.0.0.dist-info/LICENSE
dependency_analyzer-1.0.0.dist-info/METADATA
dependency_analyzer-1.0.0.dist-info/WHEEL
dependency_analyzer-1.0.0.dist-info/top_level.txt
dependency_analyzer-1.0.0.dist-info/RECORD
