Metadata-Version: 2.1
Name: dependency_analyzer
Version: 1.0.0
Summary: Analyzer of dependencies
Author: Marco Rossi
Requires-Python: >=3.7
License-File: LICENSE
Provides-Extra: test
Requires-Dist: pytest ; extra == 'test'
